mkdocs_rss_plugin/__about__.py
mkdocs_rss_plugin/__init__.py
mkdocs_rss_plugin/_version.py
mkdocs_rss_plugin/config.py
mkdocs_rss_plugin/constants.py
mkdocs_rss_plugin/models.py
mkdocs_rss_plugin/plugin.py
mkdocs_rss_plugin/timezoner.py
mkdocs_rss_plugin/util.py
mkdocs_rss_plugin/git_manager/__init__.py
mkdocs_rss_plugin/git_manager/ci.py
mkdocs_rss_plugin/integrations/__init__.py
mkdocs_rss_plugin/integrations/theme_material_base.py
mkdocs_rss_plugin/integrations/theme_material_blog_plugin.py
mkdocs_rss_plugin/integrations/theme_material_social_plugin.py
mkdocs_rss_plugin/templates/rss.xml.jinja2
mkdocs_rss_plugin-1.17.8.dist-info/licenses/LICENSE
mkdocs_rss_plugin-1.17.8.dist-info/METADATA
mkdocs_rss_plugin-1.17.8.dist-info/WHEEL
mkdocs_rss_plugin-1.17.8.dist-info/entry_points.txt
mkdocs_rss_plugin-1.17.8.dist-info/top_level.txt
mkdocs_rss_plugin-1.17.8.dist-info/RECORD
