Metadata-Version: 2.4
Name: mkdocs-rss-plugin
Version: 1.17.8
Summary: MkDocs plugin to generate RSS and JSON feeds using Mkdocs site configuration, git log and Mkdocs pages'meta.
Author-email: Julien Moura <dev@ingeoveritas.com>
Maintainer-email: Julien Moura <dev@ingeoveritas.com>
License-Expression: MIT
Project-URL: Changelog, https://github.com/guts/mkdocs-rss-plugin/blob/main/CHANGELOG.md
Project-URL: Documentation, https://guts.github.io/mkdocs-rss-plugin/
Project-URL: Homepage, https://guts.github.io/mkdocs-rss-plugin/
Project-URL: Issues, https://github.com/guts/mkdocs-rss-plugin/issues/
Project-URL: releasenotes, https://github.com/guts/mkdocs-rss-plugin/releases/latest
Project-URL: Repository, https://github.com/guts/mkdocs-rss-plugin/
Keywords: atom,documentation,feed,git,json-feed,mkdocs,plugin,rss
Classifier: Development Status :: 5 - Production/Stable
Classifier: Intended Audience :: Developers
Classifier: Intended Audience :: Information Technology
Classifier: Operating System :: OS Independent
Classifier: Programming Language :: Python :: 3
Classifier: Programming Language :: Python :: 3.10
Classifier: Programming Language :: Python :: 3.11
Classifier: Programming Language :: Python :: 3.12
Classifier: Programming Language :: Python :: 3.13
Classifier: Topic :: Documentation
Classifier: Topic :: Software Development :: Documentation
Classifier: Topic :: Text Processing :: Markup :: Markdown
Requires-Python: >=3.10
License-File: LICENSE
Requires-Dist: CacheControl[filecache]<1,>=0.14.3
Requires-Dist: GitPython<3.2,>=3.1.45
Requires-Dist: mkdocs<2,>=1.6.1
Requires-Dist: requests<3,>=2.32.5
Requires-Dist: tzdata<2026,>=2024; sys_platform == "win32"
Provides-Extra: dev
Requires-Dist: black>=25.9; extra == "dev"
Requires-Dist: flake8>=7.1; extra == "dev"
Requires-Dist: flake8-bugbear>=24.10; extra == "dev"
Requires-Dist: flake8-builtins>=2.5; extra == "dev"
Requires-Dist: flake8-eradicate>=1.5; extra == "dev"
Requires-Dist: flake8-isort>=6.1.1; extra == "dev"
Requires-Dist: Flake8-pyproject>=1.2.3; extra == "dev"
Requires-Dist: pre-commit<5,>=4; extra == "dev"
Provides-Extra: docs
Requires-Dist: mkdocs-git-committers-plugin-2<2.6,>=2.4.1; extra == "docs"
Requires-Dist: mkdocs-git-revision-date-localized-plugin<1.6,>=1.3; extra == "docs"
Requires-Dist: mkdocs-material[imaging]<9.8,>=9.7; extra == "docs"
Requires-Dist: mkdocs-minify-plugin<0.9,>=0.8; extra == "docs"
Requires-Dist: mkdocstrings-python<2.1,>=1.16.2; extra == "docs"
Requires-Dist: termynal<0.14,>=0.12.2; extra == "docs"
Provides-Extra: test
Requires-Dist: feedparser<6.1,>=6.0.12; extra == "test"
Requires-Dist: jsonfeed-util<2,>=1.2; extra == "test"
Requires-Dist: mkdocs-material[imaging]<9.8,>=9.7; extra == "test"
Requires-Dist: pytest-cov<8,>=6.9.1; extra == "test"
Requires-Dist: validator-collection<1.6,>=1.5; extra == "test"
Dynamic: license-file
